{
	"packages": [{
		"name": "aerobot",
		"maintainer": "okhiroyuki",
		"websiteURL": "https://lets.makewitharduino.com",
		"email": "ok.okada.hiroyuki@gmail.com.com",
		"help": {
			"online": "https://lets.makewitharduino.com"
		},
		"platforms": [{
			"name": "AERobot AVR Boards",
			"architecture": "avr",
			"version": "1.0.0",
			"category": "AERobot",
			"url": "https://github.com/okhiroyuki/aerobot-board-index/raw/master/boards/aerobot-1.0.0.tar.bz2",
			"archiveFileName": "aerobot-1.0.0.tar.bz2",
			"checksum": "SHA-256:8F31C84E8659617FD2B2EEE849D73BB59EBF3E13ED2ABCFDCCAC1CB7E7E50C37",
			"size": "25224",
			"help": {
				"online": "https://lets.makewitharduino.com"
			},
			"boards": [{
				"name": "AERobot"
			}],
			"toolsDependencies": [{
				"packager": "arduino",
				"name": "avr-gcc",
				"version": "4.8.1-arduino5"
			}, {
				"packager": "arduino",
				"name": "avrdude",
				"version": "6.0.1-arduino5"
			}]
		}]
    }]
}